tqsdk_zq/__init__.py
tqsdk_zq/cli.py
tqsdk_zq/config.py
tqsdk_zq/exceptions.py
tqsdk_zq/init.py
tqsdk_zq/manage_zq_history.py
tqsdk_zq/manage_zq_pg.py
tqsdk_zq/manage_zq_proxy.py
tqsdk_zq/manage_zq_server.py
tqsdk_zq/start.py
tqsdk_zq/utils.py
tqsdk_zq/web.py
tqsdk_zq-1.0.3.dist-info/METADATA
tqsdk_zq-1.0.3.dist-info/WHEEL
tqsdk_zq-1.0.3.dist-info/entry_points.txt
tqsdk_zq-1.0.3.dist-info/top_level.txt
tqsdk_zq-1.0.3.dist-info/RECORD
