Metadata-Version: 2.1
Name: tqsdk-zq
Version: 1.0.3
Summary: TianQin SDK - zq lib
Home-page: https://www.shinnytech.com/tqsdk
Author: TianQin
Author-email: tianqincn@gmail.com
License: UNKNOWN
Platform: UNKNOWN
Requires-Python: >=3
Requires-Dist: tqsdk-zq-server
Requires-Dist: tqsdk-zq-pgserver
Requires-Dist: tqsdk-zq-proxy
Requires-Dist: tqsdk-zq-history
Requires-Dist: filelock
Requires-Dist: psutil
